{
  "swagger": "2.0",
  "info": {
    "title": "API",
    "description": "Public URIs for admin that return HTML",
    "version": "0.0.1"
  },
  "host": "localhost:8888",
  "basePath": "/",
  "securityDefinitions": {},
  "security": [],
  "schemes": [
    "https",
    "http"
  ],
  "consumes": [
    "application/json",
    "multipart/form-data",
    "application/x-www-form-urlencoded"
  ],
  "produces": [
    "application/json",
    "text/plain"
  ],
  "paths": {
    "/backoffice/php-info": {
      "get": {
        "tags": [],
        "summary": "Return phpinfo() HTML page",
        "description": "",
        "operationId": "getPhpInfoPage",
        "parameters": [],
        "responses": {
          "200": {
            "description": "Page successfully generated",
            "schema": {
              "type": "string"
            }
          }
        }
      }
    },
    "/backoffice/dashboard": {
      "get": {
        "tags": [],
        "summary": "Return the HTML to render the Admin Dashboard",
        "description": "",
        "operationId": "getAdminDashboard",
        "parameters": [],
        "responses": {
          "200": {
            "description": "Page successfully generated",
            "schema": {
              "type": "string"
            }
          }
        }
      }
    },
    "/backoffice/users": {
      "get": {
        "tags": [],
        "summary": "Return the HTML to render the users admin page",
        "description": "",
        "operationId": "getUsersAdminPage",
        "parameters": [],
        "responses": {
          "200": {
            "description": "Page successfully generated",
            "schema": {
              "type": "string"
            }
          }
        }
      }
    },
    "/backoffice/users/new": {
      "get": {
        "tags": [],
        "summary": "Return the HTML to render the page to create a new user",
        "description": "",
        "operationId": "getNewUserPage",
        "parameters": [],
        "responses": {
          "200": {
            "description": "Page successfully generated",
            "schema": {
              "type": "string"
            }
          }
        }
      }
    },
    "/backoffice/users/{userId}": {
      "get": {
        "tags": [],
        "summary": "Return the HTML to render the page to edit an existing user",
        "description": "",
        "operationId": "getEditUserPage",
        "parameters": [
          {
            "name": "userId",
            "in": "path",
            "description": "User ID",
            "required": true,
            "type": "integer"
          }
        ],
        "responses": {
          "200": {
            "description": "Page successfully generated",
            "schema": {
              "type": "string"
            }
          }
        }
      }
    },
    "/backoffice/articles": {
      "get": {
        "tags": [],
        "summary": "Return the HTML to render the articles page",
        "description": "",
        "operationId": "getArticlesPage",
        "parameters": [],
        "responses": {
          "200": {
            "description": "Page successfully generated",
            "schema": {
              "type": "string"
            }
          }
        }
      }
    },
    "/backoffice/articles/new": {
      "get": {
        "tags": [],
        "summary": "Return the HTML to render the new article page",
        "description": "",
        "operationId": "getNewArticlePage",
        "parameters": [],
        "responses": {
          "200": {
            "description": "Page successfully generated",
            "schema": {
              "type": "string"
            }
          }
        }
      }
    },
    "/backoffice/articles/{articleId}": {
      "get": {
        "tags": [],
        "summary": "Return the HTML to render the page to edit an existing article",
        "description": "",
        "operationId": "getEditArticlePage",
        "parameters": [
          {
            "name": "articleId",
            "in": "path",
            "description": "Article ID",
            "required": true,
            "type": "integer"
          }
        ],
        "responses": {
          "200": {
            "description": "Page successfully generated",
            "schema": {
              "type": "string"
            }
          }
        }
      }
    },
    "/backoffice/images": {
      "get": {
        "tags": [],
        "summary": "Return the HTML to render the images page",
        "description": "",
        "operationId": "getImagesPage",
        "parameters": [],
        "responses": {
          "200": {
            "description": "Page successfully generated",
            "schema": {
              "type": "string"
            }
          }
        }
      }
    },
    "/backoffice/blog-posts": {
      "get": {
        "tags": [],
        "summary": "Return the HTML to render the blog posts page",
        "description": "",
        "operationId": "getBlogPostsPage",
        "parameters": [],
        "responses": {
          "200": {
            "description": "Page successfully generated",
            "schema": {
              "type": "string"
            }
          }
        }
      }
    },
    "/backoffice/blog-posts/new": {
      "get": {
        "tags": [],
        "summary": "Return the HTML to render the new blog post page",
        "description": "",
        "operationId": "getNewBlogPostPage",
        "parameters": [],
        "responses": {
          "200": {
            "description": "Page successfully generated",
            "schema": {
              "type": "string"
            }
          }
        }
      }
    },
    "/backoffice/blog-posts/{articleId}": {
      "get": {
        "tags": [],
        "summary": "Return the HTML to render the page to edit an existing blog post",
        "description": "",
        "operationId": "getEditBlogPostPage",
        "parameters": [
          {
            "name": "articleId",
            "in": "path",
            "description": "Article ID",
            "required": true,
            "type": "integer"
          }
        ],
        "responses": {
          "200": {
            "description": "Page successfully generated",
            "schema": {
              "type": "string"
            }
          }
        }
      }
    }
  },
  "definitions": {}
}
